{
  "0.0.1": {
    "en": "First version!"
  },
  "0.0.2": {
    "en": "Changing driver icon color"
  },
  "0.0.3": {
    "en": "Replace widget preview pictures + replace driver image + Add licens comment in description"
  },
  "0.0.4": {
    "en": "Fixing the multi floor support"
  },
  "0.0.5": {
    "en": "Fixing floor mapping and switching issues"
  },
  "0.0.6": {
    "en": "Trying to fix floor finalizing by adding waittime for finalization"
  },
  "0.0.7": {
    "en": "Fix map file handling, add no-dock segmentation trigger, fix SSH reboot path, add Roborock S5 driver"
  },
  "0.0.8": {
    "en": "Add error alarm for Homey Insights, fix widget for multi-driver support"
  }
}
